accordoai/__init__.py
accordoai/chords.py
accordoai/config.py
accordoai/model_loader.py
accordoai/postprocessor.py
accordoai/predictor.py
accordoai/preprocessor.py
accordoai/models/__init__.py
accordoai/models/model.keras
accordoai/resources/__init__.py
accordoai/resources/vocab.csv
accordoai-0.2.7.dist-info/licenses/LICENSE
accordoai-0.2.7.dist-info/METADATA
accordoai-0.2.7.dist-info/WHEEL
accordoai-0.2.7.dist-info/top_level.txt
accordoai-0.2.7.dist-info/RECORD
