Metadata-Version: 2.4
Name: accordoai
Version: 0.2.7
Summary: Chord prediction model from Accordo.ai
Home-page: https://github.com/NightKing-V/Chord-Classification-Model-accordo.ai-
Author: Valenteno Lenora
Author-email: valentenocavlenora@gmail.com
Classifier: Programming Language :: Python :: 3
Classifier: License :: OSI Approved :: MIT License
Classifier: Operating System :: OS Independent
Requires-Python: >=3.7
License-File: LICENSE
Requires-Dist: tensorflow>=2.0.0
Requires-Dist: numpy
Requires-Dist: librosa
Requires-Dist: music21
Requires-Dist: filetype
Requires-Dist: pandas
Requires-Dist: scipy
Requires-Dist: numpy
Requires-Dist: moviepy
Dynamic: author
Dynamic: author-email
Dynamic: classifier
Dynamic: description
Dynamic: description-content-type
Dynamic: home-page
Dynamic: license-file
Dynamic: requires-dist
Dynamic: requires-python
Dynamic: summary
